Workbook

Sheet Settings
A1: GP Costing Calculator – Settings
A2: Blue cells on a cream fill are inputs you can change. All other sheets read from here.
A4: Setting | B4: Value | C4: Source / note
A5: VAT rate | B5: 0.2 | C5: UK standard rate on restaurant food & drink
A6: Target GP % – Food | B6: 0.7 | C6: Jelly: 65–70% typical; 70% common target
A7: Target GP % – Drink | B7: 0.7 | C7: Jelly: 65–75% typical
A8: Alert threshold (GP % below this = problem) | B8: 0.6 | C8: Jelly: below 60% signals a pricing/cost issue
A9: Default delivery commission | B9: 0.3 | C9: Deliveroo/Uber Eats ~30%; Just Eat ~14%; own site ~2%
A10: Default packaging cost per order (£) | B10: 0.5 | C10: My placeholder assumption – replace with your real figure
A13: Benchmarks (UK, 2026)
A14: Category | B14: Target GP % | C14: Alert below
A15: Food (dine-in) | B15: 65–70% | C15: 60%
A16: Beverages | B16: 65–75% | C16: 60%
A17: Delivery (after 25–35% commission) | B17: 35–40% effective | C17: 30%
A19: Method (source: Jelly Blog, GP Margin Calculator for UK Restaurants, blog.getjelly.co.uk/gp-margin-calculator-food-beverage)
A20: 1. Strip VAT: ex-VAT = inc-VAT ÷ 1.20 (use ex-VAT for costs and prices)
A21: 2. True cost = ingredient cost × (1 + waste %) [5–8% food, 1–3% sealed drinks]
A22: 3. GP % = (ex-VAT price − true cost) ÷ ex-VAT price
A23: 4. Price for target GP: ex-VAT price = true cost ÷ (1 − target GP %); × 1.20 for menu price
A24: 5. Delivery price ex-VAT = (dine-in ex-VAT price + packaging) ÷ (1 − commission)

Sheet Dish Costing
A1: Dish & Drink Costing
A2: Fill the cream cells (blue text): item, type, ingredient cost per portion EX-VAT, waste %, and current menu price INC-VAT. Rows 6–7 are examples – overwrite them.
A3: Everything else calculates. GP % uses ex-VAT figures throughout.
A5: Item | B5: Type | C5: Ingredient cost ex-VAT (£) | D5: Waste % | E5: True cost (£) | F5: Menu price inc-VAT (£) | G5: Price ex-VAT (£) | H5: GP (£) | I5: GP % | J5: Target GP % | K5: Status | L5: Suggested price ex-VAT (£) | M5: Suggested menu price inc-VAT (£)
A6: Example dish | B6: Food | C6: 4.5 | D6: 0.06 | E6: =IF(OR($A6="",$C6=""),"",C6*(1+N(D6))) -> 4.77 | F6: 18 | G6: =IF(OR($A6="",$C6=""),"",IF(F6="","",F6/(1+Settings!$B$5))) -> 15 | H6: =IF(OR($A6="",$C6=""),"",IF(G6="","",G6-E6)) -> 10.23 | I6: =IF(OR($A6="",$C6=""),"",IF(G6="","",IF(G6=0,0,H6/G6))) -> 0.682 | J6: =IF(OR($A6="",$C6=""),"",IF(B6="Drink",Settings!$B$7,Settings!$B$6)) -> 0.7 | K6: =IF(OR($A6="",$C6=""),"",IF(I6="","",IF(I6<Settings!$B$8,"BELOW ALERT",IF(I6<J6,"Under target","On target")))) -> Under target | L6: =IF(OR($A6="",$C6=""),"",E6/(1-J6)) -> 15.9 | M6: =IF(OR($A6="",$C6=""),"",L6*(1+Settings!$B$5)) -> 19.08
A7: Example house wine (bottle) | B7: Drink | C7: 6 | D7: 0.02 | E7: =IF(OR($A7="",$C7=""),"",C7*(1+N(D7))) -> 6.12 | F7: 28.8 | G7: =IF(OR($A7="",$C7=""),"",IF(F7="","",F7/(1+Settings!$B$5))) -> 24 | H7: =IF(OR($A7="",$C7=""),"",IF(G7="","",G7-E7)) -> 17.88 | I7: =IF(OR($A7="",$C7=""),"",IF(G7="","",IF(G7=0,0,H7/G7))) -> 0.745 | J7: =IF(OR($A7="",$C7=""),"",IF(B7="Drink",Settings!$B$7,Settings!$B$6)) -> 0.7 | K7: =IF(OR($A7="",$C7=""),"",IF(I7="","",IF(I7<Settings!$B$8,"BELOW ALERT",IF(I7<J7,"Under target","On target")))) -> On target | L7: =IF(OR($A7="",$C7=""),"",E7/(1-J7)) -> 20.4 | M7: =IF(OR($A7="",$C7=""),"",L7*(1+Settings!$B$5)) -> 24.48
E8: =IF(OR($A8="",$C8=""),"",C8*(1+N(D8))) | G8: =IF(OR($A8="",$C8=""),"",IF(F8="","",F8/(1+Settings!$B$5))) | H8: =IF(OR($A8="",$C8=""),"",IF(G8="","",G8-E8)) | I8: =IF(OR($A8="",$C8=""),"",IF(G8="","",IF(G8=0,0,H8/G8))) | J8: =IF(OR($A8="",$C8=""),"",IF(B8="Drink",Settings!$B$7,Settings!$B$6)) | K8: =IF(OR($A8="",$C8=""),"",IF(I8="","",IF(I8<Settings!$B$8,"BELOW ALERT",IF(I8<J8,"Under target","On target")))) | L8: =IF(OR($A8="",$C8=""),"",E8/(1-J8)) | M8: =IF(OR($A8="",$C8=""),"",L8*(1+Settings!$B$5))
E9: =IF(OR($A9="",$C9=""),"",C9*(1+N(D9))) | G9: =IF(OR($A9="",$C9=""),"",IF(F9="","",F9/(1+Settings!$B$5))) | H9: =IF(OR($A9="",$C9=""),"",IF(G9="","",G9-E9)) | I9: =IF(OR($A9="",$C9=""),"",IF(G9="","",IF(G9=0,0,H9/G9))) | J9: =IF(OR($A9="",$C9=""),"",IF(B9="Drink",Settings!$B$7,Settings!$B$6)) | K9: =IF(OR($A9="",$C9=""),"",IF(I9="","",IF(I9<Settings!$B$8,"BELOW ALERT",IF(I9<J9,"Under target","On target")))) | L9: =IF(OR($A9="",$C9=""),"",E9/(1-J9)) | M9: =IF(OR($A9="",$C9=""),"",L9*(1+Settings!$B$5))
E10: =IF(OR($A10="",$C10=""),"",C10*(1+N(D10))) | G10: =IF(OR($A10="",$C10=""),"",IF(F10="","",F10/(1+Settings!$B$5))) | H10: =IF(OR($A10="",$C10=""),"",IF(G10="","",G10-E10)) | I10: =IF(OR($A10="",$C10=""),"",IF(G10="","",IF(G10=0,0,H10/G10))) | J10: =IF(OR($A10="",$C10=""),"",IF(B10="Drink",Settings!$B$7,Settings!$B$6)) | K10: =IF(OR($A10="",$C10=""),"",IF(I10="","",IF(I10<Settings!$B$8,"BELOW ALERT",IF(I10<J10,"Under target","On target")))) | L10: =IF(OR($A10="",$C10=""),"",E10/(1-J10)) | M10: =IF(OR($A10="",$C10=""),"",L10*(1+Settings!$B$5))
E11: =IF(OR($A11="",$C11=""),"",C11*(1+N(D11))) | G11: =IF(OR($A11="",$C11=""),"",IF(F11="","",F11/(1+Settings!$B$5))) | H11: =IF(OR($A11="",$C11=""),"",IF(G11="","",G11-E11)) | I11: =IF(OR($A11="",$C11=""),"",IF(G11="","",IF(G11=0,0,H11/G11))) | J11: =IF(OR($A11="",$C11=""),"",IF(B11="Drink",Settings!$B$7,Settings!$B$6)) | K11: =IF(OR($A11="",$C11=""),"",IF(I11="","",IF(I11<Settings!$B$8,"BELOW ALERT",IF(I11<J11,"Under target","On target")))) | L11: =IF(OR($A11="",$C11=""),"",E11/(1-J11)) | M11: =IF(OR($A11="",$C11=""),"",L11*(1+Settings!$B$5))
E12: =IF(OR($A12="",$C12=""),"",C12*(1+N(D12))) | G12: =IF(OR($A12="",$C12=""),"",IF(F12="","",F12/(1+Settings!$B$5))) | H12: =IF(OR($A12="",$C12=""),"",IF(G12="","",G12-E12)) | I12: =IF(OR($A12="",$C12=""),"",IF(G12="","",IF(G12=0,0,H12/G12))) | J12: =IF(OR($A12="",$C12=""),"",IF(B12="Drink",Settings!$B$7,Settings!$B$6)) | K12: =IF(OR($A12="",$C12=""),"",IF(I12="","",IF(I12<Settings!$B$8,"BELOW ALERT",IF(I12<J12,"Under target","On target")))) | L12: =IF(OR($A12="",$C12=""),"",E12/(1-J12)) | M12: =IF(OR($A12="",$C12=""),"",L12*(1+Settings!$B$5))
E13: =IF(OR($A13="",$C13=""),"",C13*(1+N(D13))) | G13: =IF(OR($A13="",$C13=""),"",IF(F13="","",F13/(1+Settings!$B$5))) | H13: =IF(OR($A13="",$C13=""),"",IF(G13="","",G13-E13)) | I13: =IF(OR($A13="",$C13=""),"",IF(G13="","",IF(G13=0,0,H13/G13))) | J13: =IF(OR($A13="",$C13=""),"",IF(B13="Drink",Settings!$B$7,Settings!$B$6)) | K13: =IF(OR($A13="",$C13=""),"",IF(I13="","",IF(I13<Settings!$B$8,"BELOW ALERT",IF(I13<J13,"Under target","On target")))) | L13: =IF(OR($A13="",$C13=""),"",E13/(1-J13)) | M13: =IF(OR($A13="",$C13=""),"",L13*(1+Settings!$B$5))
E14: =IF(OR($A14="",$C14=""),"",C14*(1+N(D14))) | G14: =IF(OR($A14="",$C14=""),"",IF(F14="","",F14/(1+Settings!$B$5))) | H14: =IF(OR($A14="",$C14=""),"",IF(G14="","",G14-E14)) | I14: =IF(OR($A14="",$C14=""),"",IF(G14="","",IF(G14=0,0,H14/G14))) | J14: =IF(OR($A14="",$C14=""),"",IF(B14="Drink",Settings!$B$7,Settings!$B$6)) | K14: =IF(OR($A14="",$C14=""),"",IF(I14="","",IF(I14<Settings!$B$8,"BELOW ALERT",IF(I14<J14,"Under target","On target")))) | L14: =IF(OR($A14="",$C14=""),"",E14/(1-J14)) | M14: =IF(OR($A14="",$C14=""),"",L14*(1+Settings!$B$5))
E15: =IF(OR($A15="",$C15=""),"",C15*(1+N(D15))) | G15: =IF(OR($A15="",$C15=""),"",IF(F15="","",F15/(1+Settings!$B$5))) | H15: =IF(OR($A15="",$C15=""),"",IF(G15="","",G15-E15)) | I15: =IF(OR($A15="",$C15=""),"",IF(G15="","",IF(G15=0,0,H15/G15))) | J15: =IF(OR($A15="",$C15=""),"",IF(B15="Drink",Settings!$B$7,Settings!$B$6)) | K15: =IF(OR($A15="",$C15=""),"",IF(I15="","",IF(I15<Settings!$B$8,"BELOW ALERT",IF(I15<J15,"Under target","On target")))) | L15: =IF(OR($A15="",$C15=""),"",E15/(1-J15)) | M15: =IF(OR($A15="",$C15=""),"",L15*(1+Settings!$B$5))
E16: =IF(OR($A16="",$C16=""),"",C16*(1+N(D16))) | G16: =IF(OR($A16="",$C16=""),"",IF(F16="","",F16/(1+Settings!$B$5))) | H16: =IF(OR($A16="",$C16=""),"",IF(G16="","",G16-E16)) | I16: =IF(OR($A16="",$C16=""),"",IF(G16="","",IF(G16=0,0,H16/G16))) | J16: =IF(OR($A16="",$C16=""),"",IF(B16="Drink",Settings!$B$7,Settings!$B$6)) | K16: =IF(OR($A16="",$C16=""),"",IF(I16="","",IF(I16<Settings!$B$8,"BELOW ALERT",IF(I16<J16,"Under target","On target")))) | L16: =IF(OR($A16="",$C16=""),"",E16/(1-J16)) | M16: =IF(OR($A16="",$C16=""),"",L16*(1+Settings!$B$5))
E17: =IF(OR($A17="",$C17=""),"",C17*(1+N(D17))) | G17: =IF(OR($A17="",$C17=""),"",IF(F17="","",F17/(1+Settings!$B$5))) | H17: =IF(OR($A17="",$C17=""),"",IF(G17="","",G17-E17)) | I17: =IF(OR($A17="",$C17=""),"",IF(G17="","",IF(G17=0,0,H17/G17))) | J17: =IF(OR($A17="",$C17=""),"",IF(B17="Drink",Settings!$B$7,Settings!$B$6)) | K17: =IF(OR($A17="",$C17=""),"",IF(I17="","",IF(I17<Settings!$B$8,"BELOW ALERT",IF(I17<J17,"Under target","On target")))) | L17: =IF(OR($A17="",$C17=""),"",E17/(1-J17)) | M17: =IF(OR($A17="",$C17=""),"",L17*(1+Settings!$B$5))
E18: =IF(OR($A18="",$C18=""),"",C18*(1+N(D18))) | G18: =IF(OR($A18="",$C18=""),"",IF(F18="","",F18/(1+Settings!$B$5))) | H18: =IF(OR($A18="",$C18=""),"",IF(G18="","",G18-E18)) | I18: =IF(OR($A18="",$C18=""),"",IF(G18="","",IF(G18=0,0,H18/G18))) | J18: =IF(OR($A18="",$C18=""),"",IF(B18="Drink",Settings!$B$7,Settings!$B$6)) | K18: =IF(OR($A18="",$C18=""),"",IF(I18="","",IF(I18<Settings!$B$8,"BELOW ALERT",IF(I18<J18,"Under target","On target")))) | L18: =IF(OR($A18="",$C18=""),"",E18/(1-J18)) | M18: =IF(OR($A18="",$C18=""),"",L18*(1+Settings!$B$5))
E19: =IF(OR($A19="",$C19=""),"",C19*(1+N(D19))) | G19: =IF(OR($A19="",$C19=""),"",IF(F19="","",F19/(1+Settings!$B$5))) | H19: =IF(OR($A19="",$C19=""),"",IF(G19="","",G19-E19)) | I19: =IF(OR($A19="",$C19=""),"",IF(G19="","",IF(G19=0,0,H19/G19))) | J19: =IF(OR($A19="",$C19=""),"",IF(B19="Drink",Settings!$B$7,Settings!$B$6)) | K19: =IF(OR($A19="",$C19=""),"",IF(I19="","",IF(I19<Settings!$B$8,"BELOW ALERT",IF(I19<J19,"Under target","On target")))) | L19: =IF(OR($A19="",$C19=""),"",E19/(1-J19)) | M19: =IF(OR($A19="",$C19=""),"",L19*(1+Settings!$B$5))
... E45: =IF(OR($A45="",$C45=""),"",C45*(1+N(D45))) | G45: =IF(OR($A45="",$C45=""),"",IF(F45="","",F45/(1+Settings!$B$5))) | H45: =IF(OR($A45="",$C45=""),"",IF(G45="","",G45-E45)) | I45: =IF(OR($A45="",$C45=""),"",IF(G45="","",IF(G45=0,0,H45/G45))) | J45: =IF(OR($A45="",$C45=""),"",IF(B45="Drink",Settings!$B$7,Settings!$B$6)) | K45: =IF(OR($A45="",$C45=""),"",IF(I45="","",IF(I45<Settings!$B$8,"BELOW ALERT",IF(I45<J45,"Under target","On target")))) | L45: =IF(OR($A45="",$C45=""),"",E45/(1-J45)) | M45: =IF(OR($A45="",$C45=""),"",L45*(1+Settings!$B$5))

Sheet Delivery
A1: Delivery Menu Pricing
A2: Items pull from 'Dish Costing'. Commission and packaging default to Settings (green) – overwrite per row if a platform differs.
A3: Delivery price (Jelly method) = (dine-in ex-VAT price + packaging) ÷ (1 − commission). That holds your £ profit; the last two columns show the price needed to hold your target GP %.
A5: Item | B5: True cost (£) | C5: Dine-in price ex-VAT (£) | D5: Packaging (£) | E5: Commission % | F5: Delivery price ex-VAT (£) | G5: Delivery price inc-VAT (£) | H5: Revenue kept after commission (£) | I5: GP (£) | J5: GP % on kept revenue | K5: Price to hold target GP % ex-VAT (£) | L5: …inc-VAT (£)
A6: =IF('Dish Costing'!A6="","",'Dish Costing'!A6) -> Example dish | B6: =IF(OR('Dish Costing'!$A6="",'Dish Costing'!$G6=""),"",'Dish Costing'!E6) -> 4.77 | C6: =IF(OR('Dish Costing'!$A6="",'Dish Costing'!$G6=""),"",'Dish Costing'!G6) -> 15 | D6: =IF(OR('Dish Costing'!$A6="",'Dish Costing'!$G6=""),"",Settings!$B$10) -> 0.5 | E6: =IF(OR('Dish Costing'!$A6="",'Dish Costing'!$G6=""),"",Settings!$B$9) -> 0.3 | F6: =IF(OR('Dish Costing'!$A6="",'Dish Costing'!$G6=""),"",(C6+D6)/(1-E6)) -> 22.142857 | G6: =IF(OR('Dish Costing'!$A6="",'Dish Costing'!$G6=""),"",F6*(1+Settings!$B$5)) -> 26.571429 | H6: =IF(OR('Dish Costing'!$A6="",'Dish Costing'!$G6=""),"",F6*(1-E6)) -> 15.5 | I6: =IF(OR('Dish Costing'!$A6="",'Dish Costing'!$G6=""),"",H6-D6-B6) -> 10.23 | J6: =IF(OR('Dish Costing'!$A6="",'Dish Costing'!$G6=""),"",IF(H6=0,0,I6/H6)) -> 0.66 | K6: =IF(OR('Dish Costing'!$A6="",'Dish Costing'!$G6=""),"",((B6+D6)/(1-'Dish Costing'!J6))/(1-E6)) -> 25.095238 | L6: =IF(OR('Dish Costing'!$A6="",'Dish Costing'!$G6=""),"",K6*(1+Settings!$B$5)) -> 30.114286
A7: =IF('Dish Costing'!A7="","",'Dish Costing'!A7) -> Example house wine (bottle) | B7: =IF(OR('Dish Costing'!$A7="",'Dish Costing'!$G7=""),"",'Dish Costing'!E7) -> 6.12 | C7: =IF(OR('Dish Costing'!$A7="",'Dish Costing'!$G7=""),"",'Dish Costing'!G7) -> 24 | D7: =IF(OR('Dish Costing'!$A7="",'Dish Costing'!$G7=""),"",Settings!$B$10) -> 0.5 | E7: =IF(OR('Dish Costing'!$A7="",'Dish Costing'!$G7=""),"",Settings!$B$9) -> 0.3 | F7: =IF(OR('Dish Costing'!$A7="",'Dish Costing'!$G7=""),"",(C7+D7)/(1-E7)) -> 35 | G7: =IF(OR('Dish Costing'!$A7="",'Dish Costing'!$G7=""),"",F7*(1+Settings!$B$5)) -> 42 | H7: =IF(OR('Dish Costing'!$A7="",'Dish Costing'!$G7=""),"",F7*(1-E7)) -> 24.5 | I7: =IF(OR('Dish Costing'!$A7="",'Dish Costing'!$G7=""),"",H7-D7-B7) -> 17.88 | J7: =IF(OR('Dish Costing'!$A7="",'Dish Costing'!$G7=""),"",IF(H7=0,0,I7/H7)) -> 0.72979592 | K7: =IF(OR('Dish Costing'!$A7="",'Dish Costing'!$G7=""),"",((B7+D7)/(1-'Dish Costing'!J7))/(1-E7)) -> 31.52381 | L7: =IF(OR('Dish Costing'!$A7="",'Dish Costing'!$G7=""),"",K7*(1+Settings!$B$5)) -> 37.828571
A8: =IF('Dish Costing'!A8="","",'Dish Costing'!A8) | B8: =IF(OR('Dish Costing'!$A8="",'Dish Costing'!$G8=""),"",'Dish Costing'!E8) | C8: =IF(OR('Dish Costing'!$A8="",'Dish Costing'!$G8=""),"",'Dish Costing'!G8) | D8: =IF(OR('Dish Costing'!$A8="",'Dish Costing'!$G8=""),"",Settings!$B$10) | E8: =IF(OR('Dish Costing'!$A8="",'Dish Costing'!$G8=""),"",Settings!$B$9) | F8: =IF(OR('Dish Costing'!$A8="",'Dish Costing'!$G8=""),"",(C8+D8)/(1-E8)) | G8: =IF(OR('Dish Costing'!$A8="",'Dish Costing'!$G8=""),"",F8*(1+Settings!$B$5)) | H8: =IF(OR('Dish Costing'!$A8="",'Dish Costing'!$G8=""),"",F8*(1-E8)) | I8: =IF(OR('Dish Costing'!$A8="",'Dish Costing'!$G8=""),"",H8-D8-B8) | J8: =IF(OR('Dish Costing'!$A8="",'Dish Costing'!$G8=""),"",IF(H8=0,0,I8/H8)) | K8: =IF(OR('Dish Costing'!$A8="",'Dish Costing'!$G8=""),"",((B8+D8)/(1-'Dish Costing'!J8))/(1-E8)) | L8: =IF(OR('Dish Costing'!$A8="",'Dish Costing'!$G8=""),"",K8*(1+Settings!$B$5))
A9: =IF('Dish Costing'!A9="","",'Dish Costing'!A9) | B9: =IF(OR('Dish Costing'!$A9="",'Dish Costing'!$G9=""),"",'Dish Costing'!E9) | C9: =IF(OR('Dish Costing'!$A9="",'Dish Costing'!$G9=""),"",'Dish Costing'!G9) | D9: =IF(OR('Dish Costing'!$A9="",'Dish Costing'!$G9=""),"",Settings!$B$10) | E9: =IF(OR('Dish Costing'!$A9="",'Dish Costing'!$G9=""),"",Settings!$B$9) | F9: =IF(OR('Dish Costing'!$A9="",'Dish Costing'!$G9=""),"",(C9+D9)/(1-E9)) | G9: =IF(OR('Dish Costing'!$A9="",'Dish Costing'!$G9=""),"",F9*(1+Settings!$B$5)) | H9: =IF(OR('Dish Costing'!$A9="",'Dish Costing'!$G9=""),"",F9*(1-E9)) | I9: =IF(OR('Dish Costing'!$A9="",'Dish Costing'!$G9=""),"",H9-D9-B9) | J9: =IF(OR('Dish Costing'!$A9="",'Dish Costing'!$G9=""),"",IF(H9=0,0,I9/H9)) | K9: =IF(OR('Dish Costing'!$A9="",'Dish Costing'!$G9=""),"",((B9+D9)/(1-'Dish Costing'!J9))/(1-E9)) | L9: =IF(OR('Dish Costing'!$A9="",'Dish Costing'!$G9=""),"",K9*(1+Settings!$B$5))
A10: =IF('Dish Costing'!A10="","",'Dish Costing'!A10) | B10: =IF(OR('Dish Costing'!$A10="",'Dish Costing'!$G10=""),"",'Dish Costing'!E10) | C10: =IF(OR('Dish Costing'!$A10="",'Dish Costing'!$G10=""),"",'Dish Costing'!G10) | D10: =IF(OR('Dish Costing'!$A10="",'Dish Costing'!$G10=""),"",Settings!$B$10) | E10: =IF(OR('Dish Costing'!$A10="",'Dish Costing'!$G10=""),"",Settings!$B$9) | F10: =IF(OR('Dish Costing'!$A10="",'Dish Costing'!$G10=""),"",(C10+D10)/(1-E10)) | G10: =IF(OR('Dish Costing'!$A10="",'Dish Costing'!$G10=""),"",F10*(1+Settings!$B$5)) | H10: =IF(OR('Dish Costing'!$A10="",'Dish Costing'!$G10=""),"",F10*(1-E10)) | I10: =IF(OR('Dish Costing'!$A10="",'Dish Costing'!$G10=""),"",H10-D10-B10) | J10: =IF(OR('Dish Costing'!$A10="",'Dish Costing'!$G10=""),"",IF(H10=0,0,I10/H10)) | K10: =IF(OR('Dish Costing'!$A10="",'Dish Costing'!$G10=""),"",((B10+D10)/(1-'Dish Costing'!J10))/(1-E10)) | L10: =IF(OR('Dish Costing'!$A10="",'Dish Costing'!$G10=""),"",K10*(1+Settings!$B$5))
A11: =IF('Dish Costing'!A11="","",'Dish Costing'!A11) | B11: =IF(OR('Dish Costing'!$A11="",'Dish Costing'!$G11=""),"",'Dish Costing'!E11) | C11: =IF(OR('Dish Costing'!$A11="",'Dish Costing'!$G11=""),"",'Dish Costing'!G11) | D11: =IF(OR('Dish Costing'!$A11="",'Dish Costing'!$G11=""),"",Settings!$B$10) | E11: =IF(OR('Dish Costing'!$A11="",'Dish Costing'!$G11=""),"",Settings!$B$9) | F11: =IF(OR('Dish Costing'!$A11="",'Dish Costing'!$G11=""),"",(C11+D11)/(1-E11)) | G11: =IF(OR('Dish Costing'!$A11="",'Dish Costing'!$G11=""),"",F11*(1+Settings!$B$5)) | H11: =IF(OR('Dish Costing'!$A11="",'Dish Costing'!$G11=""),"",F11*(1-E11)) | I11: =IF(OR('Dish Costing'!$A11="",'Dish Costing'!$G11=""),"",H11-D11-B11) | J11: =IF(OR('Dish Costing'!$A11="",'Dish Costing'!$G11=""),"",IF(H11=0,0,I11/H11)) | K11: =IF(OR('Dish Costing'!$A11="",'Dish Costing'!$G11=""),"",((B11+D11)/(1-'Dish Costing'!J11))/(1-E11)) | L11: =IF(OR('Dish Costing'!$A11="",'Dish Costing'!$G11=""),"",K11*(1+Settings!$B$5))
A12: =IF('Dish Costing'!A12="","",'Dish Costing'!A12) | B12: =IF(OR('Dish Costing'!$A12="",'Dish Costing'!$G12=""),"",'Dish Costing'!E12) | C12: =IF(OR('Dish Costing'!$A12="",'Dish Costing'!$G12=""),"",'Dish Costing'!G12) | D12: =IF(OR('Dish Costing'!$A12="",'Dish Costing'!$G12=""),"",Settings!$B$10) | E12: =IF(OR('Dish Costing'!$A12="",'Dish Costing'!$G12=""),"",Settings!$B$9) | F12: =IF(OR('Dish Costing'!$A12="",'Dish Costing'!$G12=""),"",(C12+D12)/(1-E12)) | G12: =IF(OR('Dish Costing'!$A12="",'Dish Costing'!$G12=""),"",F12*(1+Settings!$B$5)) | H12: =IF(OR('Dish Costing'!$A12="",'Dish Costing'!$G12=""),"",F12*(1-E12)) | I12: =IF(OR('Dish Costing'!$A12="",'Dish Costing'!$G12=""),"",H12-D12-B12) | J12: =IF(OR('Dish Costing'!$A12="",'Dish Costing'!$G12=""),"",IF(H12=0,0,I12/H12)) | K12: =IF(OR('Dish Costing'!$A12="",'Dish Costing'!$G12=""),"",((B12+D12)/(1-'Dish Costing'!J12))/(1-E12)) | L12: =IF(OR('Dish Costing'!$A12="",'Dish Costing'!$G12=""),"",K12*(1+Settings!$B$5))
A13: =IF('Dish Costing'!A13="","",'Dish Costing'!A13) | B13: =IF(OR('Dish Costing'!$A13="",'Dish Costing'!$G13=""),"",'Dish Costing'!E13) | C13: =IF(OR('Dish Costing'!$A13="",'Dish Costing'!$G13=""),"",'Dish Costing'!G13) | D13: =IF(OR('Dish Costing'!$A13="",'Dish Costing'!$G13=""),"",Settings!$B$10) | E13: =IF(OR('Dish Costing'!$A13="",'Dish Costing'!$G13=""),"",Settings!$B$9) | F13: =IF(OR('Dish Costing'!$A13="",'Dish Costing'!$G13=""),"",(C13+D13)/(1-E13)) | G13: =IF(OR('Dish Costing'!$A13="",'Dish Costing'!$G13=""),"",F13*(1+Settings!$B$5)) | H13: =IF(OR('Dish Costing'!$A13="",'Dish Costing'!$G13=""),"",F13*(1-E13)) | I13: =IF(OR('Dish Costing'!$A13="",'Dish Costing'!$G13=""),"",H13-D13-B13) | J13: =IF(OR('Dish Costing'!$A13="",'Dish Costing'!$G13=""),"",IF(H13=0,0,I13/H13)) | K13: =IF(OR('Dish Costing'!$A13="",'Dish Costing'!$G13=""),"",((B13+D13)/(1-'Dish Costing'!J13))/(1-E13)) | L13: =IF(OR('Dish Costing'!$A13="",'Dish Costing'!$G13=""),"",K13*(1+Settings!$B$5))
A14: =IF('Dish Costing'!A14="","",'Dish Costing'!A14) | B14: =IF(OR('Dish Costing'!$A14="",'Dish Costing'!$G14=""),"",'Dish Costing'!E14) | C14: =IF(OR('Dish Costing'!$A14="",'Dish Costing'!$G14=""),"",'Dish Costing'!G14) | D14: =IF(OR('Dish Costing'!$A14="",'Dish Costing'!$G14=""),"",Settings!$B$10) | E14: =IF(OR('Dish Costing'!$A14="",'Dish Costing'!$G14=""),"",Settings!$B$9) | F14: =IF(OR('Dish Costing'!$A14="",'Dish Costing'!$G14=""),"",(C14+D14)/(1-E14)) | G14: =IF(OR('Dish Costing'!$A14="",'Dish Costing'!$G14=""),"",F14*(1+Settings!$B$5)) | H14: =IF(OR('Dish Costing'!$A14="",'Dish Costing'!$G14=""),"",F14*(1-E14)) | I14: =IF(OR('Dish Costing'!$A14="",'Dish Costing'!$G14=""),"",H14-D14-B14) | J14: =IF(OR('Dish Costing'!$A14="",'Dish Costing'!$G14=""),"",IF(H14=0,0,I14/H14)) | K14: =IF(OR('Dish Costing'!$A14="",'Dish Costing'!$G14=""),"",((B14+D14)/(1-'Dish Costing'!J14))/(1-E14)) | L14: =IF(OR('Dish Costing'!$A14="",'Dish Costing'!$G14=""),"",K14*(1+Settings!$B$5))
A15: =IF('Dish Costing'!A15="","",'Dish Costing'!A15) | B15: =IF(OR('Dish Costing'!$A15="",'Dish Costing'!$G15=""),"",'Dish Costing'!E15) | C15: =IF(OR('Dish Costing'!$A15="",'Dish Costing'!$G15=""),"",'Dish Costing'!G15) | D15: =IF(OR('Dish Costing'!$A15="",'Dish Costing'!$G15=""),"",Settings!$B$10) | E15: =IF(OR('Dish Costing'!$A15="",'Dish Costing'!$G15=""),"",Settings!$B$9) | F15: =IF(OR('Dish Costing'!$A15="",'Dish Costing'!$G15=""),"",(C15+D15)/(1-E15)) | G15: =IF(OR('Dish Costing'!$A15="",'Dish Costing'!$G15=""),"",F15*(1+Settings!$B$5)) | H15: =IF(OR('Dish Costing'!$A15="",'Dish Costing'!$G15=""),"",F15*(1-E15)) | I15: =IF(OR('Dish Costing'!$A15="",'Dish Costing'!$G15=""),"",H15-D15-B15) | J15: =IF(OR('Dish Costing'!$A15="",'Dish Costing'!$G15=""),"",IF(H15=0,0,I15/H15)) | K15: =IF(OR('Dish Costing'!$A15="",'Dish Costing'!$G15=""),"",((B15+D15)/(1-'Dish Costing'!J15))/(1-E15)) | L15: =IF(OR('Dish Costing'!$A15="",'Dish Costing'!$G15=""),"",K15*(1+Settings!$B$5))
A16: =IF('Dish Costing'!A16="","",'Dish Costing'!A16) | B16: =IF(OR('Dish Costing'!$A16="",'Dish Costing'!$G16=""),"",'Dish Costing'!E16) | C16: =IF(OR('Dish Costing'!$A16="",'Dish Costing'!$G16=""),"",'Dish Costing'!G16) | D16: =IF(OR('Dish Costing'!$A16="",'Dish Costing'!$G16=""),"",Settings!$B$10) | E16: =IF(OR('Dish Costing'!$A16="",'Dish Costing'!$G16=""),"",Settings!$B$9) | F16: =IF(OR('Dish Costing'!$A16="",'Dish Costing'!$G16=""),"",(C16+D16)/(1-E16)) | G16: =IF(OR('Dish Costing'!$A16="",'Dish Costing'!$G16=""),"",F16*(1+Settings!$B$5)) | H16: =IF(OR('Dish Costing'!$A16="",'Dish Costing'!$G16=""),"",F16*(1-E16)) | I16: =IF(OR('Dish Costing'!$A16="",'Dish Costing'!$G16=""),"",H16-D16-B16) | J16: =IF(OR('Dish Costing'!$A16="",'Dish Costing'!$G16=""),"",IF(H16=0,0,I16/H16)) | K16: =IF(OR('Dish Costing'!$A16="",'Dish Costing'!$G16=""),"",((B16+D16)/(1-'Dish Costing'!J16))/(1-E16)) | L16: =IF(OR('Dish Costing'!$A16="",'Dish Costing'!$G16=""),"",K16*(1+Settings!$B$5))
A17: =IF('Dish Costing'!A17="","",'Dish Costing'!A17) | B17: =IF(OR('Dish Costing'!$A17="",'Dish Costing'!$G17=""),"",'Dish Costing'!E17) | C17: =IF(OR('Dish Costing'!$A17="",'Dish Costing'!$G17=""),"",'Dish Costing'!G17) | D17: =IF(OR('Dish Costing'!$A17="",'Dish Costing'!$G17=""),"",Settings!$B$10) | E17: =IF(OR('Dish Costing'!$A17="",'Dish Costing'!$G17=""),"",Settings!$B$9) | F17: =IF(OR('Dish Costing'!$A17="",'Dish Costing'!$G17=""),"",(C17+D17)/(1-E17)) | G17: =IF(OR('Dish Costing'!$A17="",'Dish Costing'!$G17=""),"",F17*(1+Settings!$B$5)) | H17: =IF(OR('Dish Costing'!$A17="",'Dish Costing'!$G17=""),"",F17*(1-E17)) | I17: =IF(OR('Dish Costing'!$A17="",'Dish Costing'!$G17=""),"",H17-D17-B17) | J17: =IF(OR('Dish Costing'!$A17="",'Dish Costing'!$G17=""),"",IF(H17=0,0,I17/H17)) | K17: =IF(OR('Dish Costing'!$A17="",'Dish Costing'!$G17=""),"",((B17+D17)/(1-'Dish Costing'!J17))/(1-E17)) | L17: =IF(OR('Dish Costing'!$A17="",'Dish Costing'!$G17=""),"",K17*(1+Settings!$B$5))
... A45: =IF('Dish Costing'!A45="","",'Dish Costing'!A45) | B45: =IF(OR('Dish Costing'!$A45="",'Dish Costing'!$G45=""),"",'Dish Costing'!E45) | C45: =IF(OR('Dish Costing'!$A45="",'Dish Costing'!$G45=""),"",'Dish Costing'!G45) | D45: =IF(OR('Dish Costing'!$A45="",'Dish Costing'!$G45=""),"",Settings!$B$10) | E45: =IF(OR('Dish Costing'!$A45="",'Dish Costing'!$G45=""),"",Settings!$B$9) | F45: =IF(OR('Dish Costing'!$A45="",'Dish Costing'!$G45=""),"",(C45+D45)/(1-E45)) | G45: =IF(OR('Dish Costing'!$A45="",'Dish Costing'!$G45=""),"",F45*(1+Settings!$B$5)) | H45: =IF(OR('Dish Costing'!$A45="",'Dish Costing'!$G45=""),"",F45*(1-E45)) | I45: =IF(OR('Dish Costing'!$A45="",'Dish Costing'!$G45=""),"",H45-D45-B45) | J45: =IF(OR('Dish Costing'!$A45="",'Dish Costing'!$G45=""),"",IF(H45=0,0,I45/H45)) | K45: =IF(OR('Dish Costing'!$A45="",'Dish Costing'!$G45=""),"",((B45+D45)/(1-'Dish Costing'!J45))/(1-E45)) | L45: =IF(OR('Dish Costing'!$A45="",'Dish Costing'!$G45=""),"",K45*(1+Settings!$B$5))
